ff/__init__.py
ff/ff_combinatorics.py
ff/ff_distance_measures.py
ff/ff_graph_theory.py
ff/ff_lib.py
ff/ff_random_states.py
ff/ff_utils.py
free_fermion_lib-1.2.2.dist-info/licenses/LICENSE
free_fermion_lib-1.2.2.dist-info/METADATA
free_fermion_lib-1.2.2.dist-info/WHEEL
free_fermion_lib-1.2.2.dist-info/top_level.txt
free_fermion_lib-1.2.2.dist-info/RECORD
