Metadata-Version: 2.4
Name: free-fermion-lib
Version: 1.2.2
Summary: A comprehensive Python library for free fermion systems
Home-page: https://github.com/jdwhitfield/free-fermion-lib
Author: James D. Whitfield
Author-email: "James D. Whitfield" <James.D.Whitfield@dartmouth.edu>
License: MIT
Project-URL: Homepage, https://github.com/jdwhitfield/free-fermion-lib
Project-URL: Documentation, https://free-fermion-lib.readthedocs.io/
Project-URL: Repository, https://github.com/jdwhitfield/free-fermion-lib
Project-URL: Bug Reports, https://github.com/jdwhitfield/free-fermion-lib/issues
Keywords: quantum physics,free fermions,combinatorics,graph theory,pfaffian,quantum computing,linear algebra,symplectic
Classifier: Development Status :: 4 - Beta
Classifier: Intended Audience :: Science/Research
Classifier: Topic :: Scientific/Engineering :: Physics
Classifier: Topic :: Scientific/Engineering :: Mathematics
Classifier: License :: OSI Approved :: MIT License
Classifier: Programming Language :: Python :: 3
Classifier: Programming Language :: Python :: 3.8
Classifier: Programming Language :: Python :: 3.9
Classifier: Programming Language :: Python :: 3.10
Classifier: Programming Language :: Python :: 3.11
Classifier: Programming Language :: Python :: 3.12
Requires-Python: >=3.8
License-File: LICENSE
Requires-Dist: numpy>=1.20.0
Requires-Dist: scipy>=1.7.0
Requires-Dist: networkx>=2.6.0
Requires-Dist: matplotlib>=3.3.0
Requires-Dist: stim>=1.0.0
Provides-Extra: dev
Requires-Dist: pytest>=6.0; extra == "dev"
Requires-Dist: pytest-cov>=2.0; extra == "dev"
Requires-Dist: black>=21.0; extra == "dev"
Requires-Dist: flake8>=3.8; extra == "dev"
Requires-Dist: mypy>=0.800; extra == "dev"
Provides-Extra: docs
Requires-Dist: sphinx>=4.0; extra == "docs"
Requires-Dist: sphinx-rtd-theme>=1.0; extra == "docs"
Requires-Dist: nbsphinx>=0.8; extra == "docs"
Dynamic: author
Dynamic: home-page
Dynamic: license-file
Dynamic: requires-python
